pyfrom/__init__.py
pyfrom/cli.py
pyfrom-0.1.0.dist-info/METADATA
pyfrom-0.1.0.dist-info/WHEEL
pyfrom-0.1.0.dist-info/entry_points.txt
pyfrom-0.1.0.dist-info/top_level.txt
pyfrom-0.1.0.dist-info/RECORD
