Metadata-Version: 2.4
Name: pyfrom
Version: 0.1.0
Summary: Run Python code directly from URLs
Author-email: Your Name <your.email@example.com>
License: MIT
Classifier: Programming Language :: Python :: 3
Classifier: License :: OSI Approved :: MIT License
Requires-Python: >=3.6
Requires-Dist: requests
Requires-Dist: click
